Metadata-Version: 2.1
Name: py-mess-server-kuznetsov
Version: 3.3.9
Summary: Mess Server
Home-page: UNKNOWN
Author: Sergey Kuznetsov
Author-email: ksn1974@mail.ru
License: UNKNOWN
Platform: UNKNOWN
Requires-Dist: PyQt5
Requires-Dist: sqlalchemy
Requires-Dist: pycryptodome
Requires-Dist: pycryptodomex
